README.rst
pyproject.toml
setup.py
objt/__init__.py
objt/errors.py
objt.egg-info/PKG-INFO
objt.egg-info/SOURCES.txt
objt.egg-info/dependency_links.txt
objt.egg-info/top_level.txt
objt.egg-info/zip-safe